[
  {
    "keyword": "prue",
    "score": 4820.124907036702
  },
  {
    "keyword": "phoebe",
    "score": 2087.2640463680987
  },
  {
    "keyword": "piper",
    "score": 1545.7576594002178
  },
  {
    "keyword": "paige",
    "score": 1005.0215699212554
  },
  {
    "keyword": "charmed ones",
    "score": 447.22233506521724
  },
  {
    "keyword": "whitelighter",
    "score": 431.6125866508501
  },
  {
    "keyword": "leo",
    "score": 331.6484346973613
  },
  {
    "keyword": "vanquish",
    "score": 308.9006518019921
  },
  {
    "keyword": "power three",
    "score": 189.21151610186658
  },
  {
    "keyword": "mean",
    "score": 160.48134236725676
  },
  {
    "keyword": "really",
    "score": 147.0585518200304
  },
  {
    "keyword": "vanquishing",
    "score": 143.0909268989161
  },
  {
    "keyword": "wyatt",
    "score": 136.62157881273114
  },
  {
    "keyword": "book shadows",
    "score": 133.86869459612876
  },
  {
    "keyword": "halliwell",
    "score": 133.4146296520407
  },
  {
    "keyword": "belthazor",
    "score": 126.18068109117381
  },
  {
    "keyword": "witches",
    "score": 124.55200588635294
  },
  {
    "keyword": "magic school",
    "score": 121.73338322311112
  },
  {
    "keyword": "demon",
    "score": 98.7680988338313
  },
  {
    "keyword": "orb",
    "score": 93.42274347131294
  },
  {
    "keyword": "find",
    "score": 92.15484721885733
  },
  {
    "keyword": "something",
    "score": 87.40298564260166
  },
  {
    "keyword": "powers",
    "score": 79.05721796158244
  },
  {
    "keyword": "spell",
    "score": 71.8889839422128
  },
  {
    "keyword": "cole",
    "score": 70.2603920914556
  },
  {
    "keyword": "wait",
    "score": 65.6788464617894
  },
  {
    "keyword": "charmed",
    "score": 63.18301095712114
  },
  {
    "keyword": "witch",
    "score": 58.780401049262615
  },
  {
    "keyword": "warlock",
    "score": 54.70097761887046
  },
  {
    "keyword": "elders",
    "score": 51.95557737523375
  },
  {
    "keyword": "still",
    "score": 51.27344346553667
  },
  {
    "keyword": "zankou",
    "score": 46.981473293597155
  },
  {
    "keyword": "say",
    "score": 46.44402100383602
  },
  {
    "keyword": "potion",
    "score": 44.525024634612386
  },
  {
    "keyword": "never",
    "score": 43.45093550201564
  },
  {
    "keyword": "even",
    "score": 39.58165609744544
  },
  {
    "keyword": "little",
    "score": 39.161819563381975
  },
  {
    "keyword": "anything",
    "score": 37.84385519134255
  },
  {
    "keyword": "work",
    "score": 36.491495995731725
  },
  {
    "keyword": "avatars",
    "score": 35.408508672266
  },
  {
    "keyword": "way",
    "score": 33.89466698073293
  },
  {
    "keyword": "happened",
    "score": 32.91826075162846
  },
  {
    "keyword": "billie",
    "score": 32.38388498749602
  },
  {
    "keyword": "said",
    "score": 32.310999638161086
  },
  {
    "keyword": "power",
    "score": 32.0718625733885
  },
  {
    "keyword": "actually",
    "score": 31.212594954731735
  },
  {
    "keyword": "demons",
    "score": 30.67924985033534
  },
  {
    "keyword": "darryl",
    "score": 30.3028338678275
  },
  {
    "keyword": "nothing",
    "score": 29.08985437359225
  },
  {
    "keyword": "please",
    "score": 29.024296484220685
  },
  {
    "keyword": "evil",
    "score": 28.97798522386229
  },
  {
    "keyword": "magic",
    "score": 28.2727398761036
  },
  {
    "keyword": "piper piper",
    "score": 27.406506660069958
  },
  {
    "keyword": "keep",
    "score": 26.524254700210935
  },
  {
    "keyword": "better",
    "score": 26.344058098177655
  },
  {
    "keyword": "barbas",
    "score": 26.18962663773943
  },
  {
    "keyword": "kill",
    "score": 26.173804696855807
  },
  {
    "keyword": "much",
    "score": 25.907150259275188
  },
  {
    "keyword": "grams",
    "score": 25.6551950635629
  },
  {
    "keyword": "thought",
    "score": 25.141408242275265
  },
  {
    "keyword": "piper leo",
    "score": 24.91226337166598
  },
  {
    "keyword": "trying",
    "score": 24.48086823232464
  },
  {
    "keyword": "believe",
    "score": 24.204174664843787
  },
  {
    "keyword": "everything",
    "score": 24.046502728205546
  },
  {
    "keyword": "talk",
    "score": 23.17948979929654
  },
  {
    "keyword": "kind",
    "score": 22.378101874350243
  },
  {
    "keyword": "great",
    "score": 22.07732287640205
  },
  {
    "keyword": "thank",
    "score": 21.89923168862619
  },
  {
    "keyword": "christy",
    "score": 21.198194727171167
  },
  {
    "keyword": "give",
    "score": 21.028264027043193
  },
  {
    "keyword": "sisters",
    "score": 20.722707102608243
  },
  {
    "keyword": "god",
    "score": 20.43063545384257
  },
  {
    "keyword": "pheebs",
    "score": 19.38228266116814
  },
  {
    "keyword": "vanquished",
    "score": 19.094181670388895
  },
  {
    "keyword": "understand",
    "score": 18.989238271001998
  },
  {
    "keyword": "try",
    "score": 18.363986147916396
  },
  {
    "keyword": "triad",
    "score": 18.15836209327751
  },
  {
    "keyword": "away",
    "score": 18.015979644536742
  },
  {
    "keyword": "warlocks",
    "score": 17.82279347248446
  },
  {
    "keyword": "first",
    "score": 17.708448275426957
  },
  {
    "keyword": "supposed",
    "score": 17.453984870274105
  },
  {
    "keyword": "told",
    "score": 17.441720177232508
  },
  {
    "keyword": "love",
    "score": 17.437776720243537
  },
  {
    "keyword": "piper phoebe",
    "score": 17.310856143257247
  },
  {
    "keyword": "gideon",
    "score": 17.018074068457967
  },
  {
    "keyword": "premonition",
    "score": 17.014781777647332
  },
  {
    "keyword": "thanks",
    "score": 16.893404528199927
  },
  {
    "keyword": "phoebe phoebe",
    "score": 16.715588022177702
  },
  {
    "keyword": "book",
    "score": 16.48006433996282
  },
  {
    "keyword": "prue prue",
    "score": 16.42608760791901
  },
  {
    "keyword": "phoebe paige",
    "score": 16.25124387117992
  },
  {
    "keyword": "remember",
    "score": 16.092143586627632
  },
  {
    "keyword": "life",
    "score": 15.947984820134222
  },
  {
    "keyword": "call",
    "score": 15.921376202969894
  },
  {
    "keyword": "save",
    "score": 15.580622220733613
  },
  {
    "keyword": "enough",
    "score": 15.44459819730228
  },
  {
    "keyword": "last",
    "score": 15.13049159474957
  },
  {
    "keyword": "demonic",
    "score": 14.87546742814205
  },
  {
    "keyword": "sister",
    "score": 14.653816778990125
  },
  {
    "keyword": "ever",
    "score": 14.53124195319404
  },
  {
    "keyword": "feel",
    "score": 14.37906079889643
  },
  {
    "keyword": "talking",
    "score": 14.240047324814423
  },
  {
    "keyword": "idea",
    "score": 13.801166153486518
  },
  {
    "keyword": "bad",
    "score": 13.452464830621835
  },
  {
    "keyword": "leo leo",
    "score": 13.309570651797124
  },
  {
    "keyword": "three",
    "score": 13.268942049817527
  },
  {
    "keyword": "guess",
    "score": 13.1064494426251
  },
  {
    "keyword": "around",
    "score": 12.967118897304358
  },
  {
    "keyword": "getting",
    "score": 12.894753227732835
  },
  {
    "keyword": "done",
    "score": 12.66709120090447
  },
  {
    "keyword": "always",
    "score": 12.598059936801112
  },
  {
    "keyword": "already",
    "score": 12.46079363741858
  },
  {
    "keyword": "wanted",
    "score": 12.421500301327164
  },
  {
    "keyword": "prue piper",
    "score": 12.313524708314368
  },
  {
    "keyword": "cast spell",
    "score": 12.008159099852778
  },
  {
    "keyword": "shadows",
    "score": 11.765516215850297
  },
  {
    "keyword": "stay",
    "score": 11.723467072375621
  },
  {
    "keyword": "prue halliwell",
    "score": 11.405445560832902
  },
  {
    "keyword": "else",
    "score": 11.313551281825438
  },
  {
    "keyword": "underworld",
    "score": 11.227872766006607
  },
  {
    "keyword": "found",
    "score": 11.102287216064012
  },
  {
    "keyword": "wrong",
    "score": 11.08143929772361
  },
  {
    "keyword": "leave",
    "score": 10.971772093393787
  },
  {
    "keyword": "least",
    "score": 10.90471169126711
  },
  {
    "keyword": "worry",
    "score": 10.64100672493973
  },
  {
    "keyword": "ones",
    "score": 10.464631339955085
  },
  {
    "keyword": "care",
    "score": 10.373794805766972
  },
  {
    "keyword": "means",
    "score": 10.341204196752381
  },
  {
    "keyword": "sure",
    "score": 10.164547408144474
  },
  {
    "keyword": "phoebe halliwell",
    "score": 10.101628178935679
  },
  {
    "keyword": "hurt",
    "score": 10.097663624751814
  },
  {
    "keyword": "problem",
    "score": 10.039340363774528
  },
  {
    "keyword": "looking",
    "score": 10.032648588817146
  },
  {
    "keyword": "exactly",
    "score": 9.929013295219924
  },
  {
    "keyword": "home",
    "score": 9.598609636138075
  },
  {
    "keyword": "yet",
    "score": 9.512784299645825
  },
  {
    "keyword": "saw",
    "score": 9.44957439193124
  },
  {
    "keyword": "mind",
    "score": 9.36451237230437
  },
  {
    "keyword": "another",
    "score": 9.283286058553438
  },
  {
    "keyword": "hell",
    "score": 9.207437385621466
  },
  {
    "keyword": "listen",
    "score": 9.181658008857971
  },
  {
    "keyword": "matter",
    "score": 9.15846033946069
  },
  {
    "keyword": "elder",
    "score": 9.014612075789106
  },
  {
    "keyword": "killed",
    "score": 8.971547886457643
  },
  {
    "keyword": "ask",
    "score": 8.965143982202989
  },
  {
    "keyword": "without",
    "score": 8.910610691375627
  },
  {
    "keyword": "yeah well",
    "score": 8.892767248220323
  },
  {
    "keyword": "chris",
    "score": 8.733847523025142
  },
  {
    "keyword": "probably",
    "score": 8.465437208258418
  },
  {
    "keyword": "since",
    "score": 8.309679321190195
  },
  {
    "keyword": "hear",
    "score": 8.28303661437629
  },
  {
    "keyword": "someone",
    "score": 8.01630561954474
  },
  {
    "keyword": "magical",
    "score": 7.9290780808299965
  },
  {
    "keyword": "manor",
    "score": 7.755541780744962
  },
  {
    "keyword": "happen",
    "score": 7.752028470710563
  },
  {
    "keyword": "together",
    "score": 7.748052724687934
  },
  {
    "keyword": "seer",
    "score": 7.743066111284038
  },
  {
    "keyword": "put",
    "score": 7.723224674216289
  },
  {
    "keyword": "fine",
    "score": 7.655226492343446
  },
  {
    "keyword": "use",
    "score": 7.595816661393904
  },
  {
    "keyword": "ready",
    "score": 7.5266171385357765
  },
  {
    "keyword": "use powers",
    "score": 7.489128538305573
  },
  {
    "keyword": "use magic",
    "score": 7.325326421439309
  },
  {
    "keyword": "dead",
    "score": 7.215703579967419
  },
  {
    "keyword": "move",
    "score": 7.142211240965897
  },
  {
    "keyword": "mom",
    "score": 7.096352169458231
  },
  {
    "keyword": "buckland",
    "score": 7.069650984126518
  },
  {
    "keyword": "knew",
    "score": 7.054626060771032
  },
  {
    "keyword": "coming",
    "score": 6.625509825762676
  },
  {
    "keyword": "used",
    "score": 6.514809777833738
  },
  {
    "keyword": "years",
    "score": 6.47626683368648
  },
  {
    "keyword": "made",
    "score": 6.417437791220412
  },
  {
    "keyword": "anymore",
    "score": 6.408442161523294
  },
  {
    "keyword": "able",
    "score": 6.374678533655303
  },
  {
    "keyword": "nexus",
    "score": 6.326571200714496
  },
  {
    "keyword": "somebody",
    "score": 6.269649153657512
  },
  {
    "keyword": "late",
    "score": 6.137447289220632
  },
  {
    "keyword": "reason",
    "score": 6.128153073086997
  },
  {
    "keyword": "nice",
    "score": 6.123468427671802
  },
  {
    "keyword": "trust",
    "score": 5.944842135504385
  },
  {
    "keyword": "day",
    "score": 5.869859799661439
  },
  {
    "keyword": "amulet",
    "score": 5.84074447389688
  },
  {
    "keyword": "family",
    "score": 5.791320288064524
  },
  {
    "keyword": "inspector",
    "score": 5.717408131557327
  },
  {
    "keyword": "potions",
    "score": 5.709839679121665
  },
  {
    "keyword": "next",
    "score": 5.540895682374239
  },
  {
    "keyword": "world",
    "score": 5.5291683441899
  },
  {
    "keyword": "whatever",
    "score": 5.469408364516011
  },
  {
    "keyword": "bring",
    "score": 5.439628525988969
  },
  {
    "keyword": "tried",
    "score": 5.4370663304678315
  },
  {
    "keyword": "later",
    "score": 5.408991489328418
  },
  {
    "keyword": "alone",
    "score": 5.378569072841617
  },
  {
    "keyword": "night",
    "score": 5.365295088002084
  },
  {
    "keyword": "stop",
    "score": 5.309986908820862
  },
  {
    "keyword": "protect",
    "score": 5.2593907709814545
  },
  {
    "keyword": "wants",
    "score": 5.202533740799819
  },
  {
    "keyword": "honey",
    "score": 5.156817763161
  },
  {
    "keyword": "seen",
    "score": 5.138907760061678
  },
  {
    "keyword": "house",
    "score": 5.079063054001132
  },
  {
    "keyword": "called",
    "score": 5.004879893838918
  }
]