[
  {
    "keyword": "galvin",
    "score": 1588.3750625692585
  },
  {
    "keyword": "mina",
    "score": 314.58397984527164
  },
  {
    "keyword": "luke",
    "score": 78.38217936938563
  },
  {
    "keyword": "ruby",
    "score": 47.13815679214703
  },
  {
    "keyword": "got",
    "score": 29.299640529546966
  },
  {
    "keyword": "rupert",
    "score": 28.372111952113187
  },
  {
    "keyword": "ally",
    "score": 18.460628502023578
  },
  {
    "keyword": "orb",
    "score": 16.788491832871063
  },
  {
    "keyword": "one",
    "score": 10.979400363884583
  },
  {
    "keyword": "mum",
    "score": 8.0299780627114
  },
  {
    "keyword": "half",
    "score": 6.142777834570997
  },
  {
    "keyword": "kill",
    "score": 4.254761568202012
  },
  {
    "keyword": "keep",
    "score": 4.031387423345448
  },
  {
    "keyword": "dad",
    "score": 3.071291443451099
  },
  {
    "keyword": "thought",
    "score": 2.769174592443519
  },
  {
    "keyword": "talk",
    "score": 2.7477329190352697
  },
  {
    "keyword": "jamie",
    "score": 2.730103458996908
  },
  {
    "keyword": "vampire",
    "score": 2.6501938864157566
  },
  {
    "keyword": "name",
    "score": 2.444820890515694
  },
  {
    "keyword": "vampires",
    "score": 2.3032518975187224
  },
  {
    "keyword": "killed",
    "score": 2.2577116403049526
  },
  {
    "keyword": "nasty",
    "score": 2.0397506946798067
  },
  {
    "keyword": "told",
    "score": 2.017094772510067
  },
  {
    "keyword": "dead",
    "score": 1.994887605553911
  },
  {
    "keyword": "angel",
    "score": 1.9595438196749448
  },
  {
    "keyword": "sword",
    "score": 1.8917399852838044
  },
  {
    "keyword": "nice",
    "score": 1.812942151513852
  },
  {
    "keyword": "seen",
    "score": 1.7957876992196264
  },
  {
    "keyword": "real",
    "score": 1.7156867464358958
  },
  {
    "keyword": "happen",
    "score": 1.7036234198774614
  },
  {
    "keyword": "hear",
    "score": 1.6846587579059993
  },
  {
    "keyword": "dracula",
    "score": 1.6549565749100086
  },
  {
    "keyword": "years",
    "score": 1.6448043810092592
  },
  {
    "keyword": "exactly",
    "score": 1.6272158410754662
  },
  {
    "keyword": "thee",
    "score": 1.6230659143514923
  },
  {
    "keyword": "word",
    "score": 1.534018698510632
  },
  {
    "keyword": "talking",
    "score": 1.524258365936201
  },
  {
    "keyword": "alice",
    "score": 1.5221366788744894
  },
  {
    "keyword": "better",
    "score": 1.424446900564566
  },
  {
    "keyword": "kin",
    "score": 1.3843982996232402
  },
  {
    "keyword": "abraham",
    "score": 1.3800193008343837
  },
  {
    "keyword": "erm",
    "score": 1.3443378500106091
  },
  {
    "keyword": "thin",
    "score": 1.275475342980979
  },
  {
    "keyword": "thou",
    "score": 1.2554487655912936
  },
  {
    "keyword": "problem",
    "score": 1.223093387467289
  },
  {
    "keyword": "jay",
    "score": 1.1998031720043245
  },
  {
    "keyword": "van",
    "score": 1.1954940177602738
  },
  {
    "keyword": "favourite",
    "score": 1.180075513105601
  },
  {
    "keyword": "may",
    "score": 1.164209111286181
  },
  {
    "keyword": "blood",
    "score": 1.1497925074888955
  },
  {
    "keyword": "eat",
    "score": 1.1405422998567958
  },
  {
    "keyword": "happened",
    "score": 1.1370549342917469
  },
  {
    "keyword": "wait",
    "score": 1.09936434075437
  },
  {
    "keyword": "safe",
    "score": 1.0978649365307085
  },
  {
    "keyword": "home",
    "score": 1.088947871486758
  },
  {
    "keyword": "pretending",
    "score": 1.0557368409803156
  },
  {
    "keyword": "karen",
    "score": 1.0375325326141682
  },
  {
    "keyword": "father",
    "score": 1.0361714426588717
  },
  {
    "keyword": "freak",
    "score": 1.034518552028589
  },
  {
    "keyword": "www com",
    "score": 0.9970354901265984
  },
  {
    "keyword": "trust",
    "score": 0.9534826356512545
  },
  {
    "keyword": "meet",
    "score": 0.9181798433068968
  },
  {
    "keyword": "ohhh",
    "score": 0.9148575018365169
  },
  {
    "keyword": "two",
    "score": 0.9059664243081544
  },
  {
    "keyword": "believe",
    "score": 0.9030768805043855
  },
  {
    "keyword": "else",
    "score": 0.8900304149990862
  },
  {
    "keyword": "anyway",
    "score": 0.8796959040218295
  },
  {
    "keyword": "cos",
    "score": 0.8499307769964564
  },
  {
    "keyword": "died",
    "score": 0.8354878847132158
  },
  {
    "keyword": "tin",
    "score": 0.8294364917780606
  },
  {
    "keyword": "human",
    "score": 0.8288074534519806
  },
  {
    "keyword": "without",
    "score": 0.8246897812324511
  },
  {
    "keyword": "wanted",
    "score": 0.8115796832504351
  },
  {
    "keyword": "dear",
    "score": 0.7994638975068211
  },
  {
    "keyword": "girl",
    "score": 0.7834992070398492
  },
  {
    "keyword": "understand",
    "score": 0.7824624633491152
  },
  {
    "keyword": "little",
    "score": 0.7785454455922862
  },
  {
    "keyword": "wrong",
    "score": 0.7615300222392525
  },
  {
    "keyword": "demon",
    "score": 0.7573880694041635
  },
  {
    "keyword": "sewer",
    "score": 0.7494918467934469
  },
  {
    "keyword": "war",
    "score": 0.7423829290690763
  },
  {
    "keyword": "start",
    "score": 0.7415542401497972
  },
  {
    "keyword": "com presents",
    "score": 0.734519699490066
  },
  {
    "keyword": "dunno",
    "score": 0.734519699490066
  },
  {
    "keyword": "choice",
    "score": 0.7341531983685275
  },
  {
    "keyword": "knew",
    "score": 0.7333945627785204
  },
  {
    "keyword": "done",
    "score": 0.7217024558893262
  },
  {
    "keyword": "julius",
    "score": 0.7099703729808355
  },
  {
    "keyword": "ate",
    "score": 0.7011519664912359
  },
  {
    "keyword": "whole",
    "score": 0.6879210770377597
  },
  {
    "keyword": "worry",
    "score": 0.6774725784285051
  },
  {
    "keyword": "com",
    "score": 0.6754949022516465
  },
  {
    "keyword": "stay",
    "score": 0.6738549062097281
  },
  {
    "keyword": "tobias",
    "score": 0.6719387517610255
  },
  {
    "keyword": "act",
    "score": 0.66460277232926
  },
  {
    "keyword": "bet",
    "score": 0.6642474725261027
  },
  {
    "keyword": "care",
    "score": 0.6526889709993299
  },
  {
    "keyword": "freaks",
    "score": 0.6500506560566248
  },
  {
    "keyword": "dna",
    "score": 0.6473845867287853
  },
  {
    "keyword": "enough",
    "score": 0.6453061598454096
  },
  {
    "keyword": "love",
    "score": 0.6419706864653764
  },
  {
    "keyword": "gone",
    "score": 0.5940446024259184
  },
  {
    "keyword": "remember",
    "score": 0.5862265311501238
  },
  {
    "keyword": "whatever",
    "score": 0.5792583617638581
  },
  {
    "keyword": "saying",
    "score": 0.5699134925584479
  },
  {
    "keyword": "ice",
    "score": 0.5658809227504529
  },
  {
    "keyword": "hell",
    "score": 0.5623081538137212
  },
  {
    "keyword": "easy",
    "score": 0.5590778318505414
  },
  {
    "keyword": "listen",
    "score": 0.5551557352994818
  },
  {
    "keyword": "god",
    "score": 0.5533157226389767
  },
  {
    "keyword": "lost",
    "score": 0.5443033614761454
  },
  {
    "keyword": "run",
    "score": 0.5442054255234757
  },
  {
    "keyword": "went",
    "score": 0.5429333071688331
  },
  {
    "keyword": "watch",
    "score": 0.5416887628928254
  },
  {
    "keyword": "welcome www",
    "score": 0.5362491449074775
  },
  {
    "keyword": "boy",
    "score": 0.5341639846523535
  },
  {
    "keyword": "fine",
    "score": 0.5333978459754948
  },
  {
    "keyword": "gonna",
    "score": 0.5333824726771782
  },
  {
    "keyword": "wires",
    "score": 0.5329526359262169
  },
  {
    "keyword": "rat",
    "score": 0.5318918593778472
  },
  {
    "keyword": "smell",
    "score": 0.523090377699306
  },
  {
    "keyword": "supposed",
    "score": 0.4959647003739989
  },
  {
    "keyword": "lovely",
    "score": 0.492709729401563
  },
  {
    "keyword": "colonial",
    "score": 0.48263663449817823
  },
  {
    "keyword": "denial",
    "score": 0.4681700867953812
  },
  {
    "keyword": "chickens",
    "score": 0.4661032864668294
  },
  {
    "keyword": "entirely",
    "score": 0.465582829855843
  },
  {
    "keyword": "took",
    "score": 0.4647715843154931
  },
  {
    "keyword": "ways",
    "score": 0.4558872546830213
  },
  {
    "keyword": "driving",
    "score": 0.44550911153200184
  },
  {
    "keyword": "hurt",
    "score": 0.4428949234348624
  },
  {
    "keyword": "friendship",
    "score": 0.4382216621499245
  },
  {
    "keyword": "maggie",
    "score": 0.4382216621499245
  },
  {
    "keyword": "worried",
    "score": 0.438183103423813
  },
  {
    "keyword": "round",
    "score": 0.43581338381718976
  },
  {
    "keyword": "kung",
    "score": 0.4338936741040887
  },
  {
    "keyword": "fault",
    "score": 0.43100135892726593
  },
  {
    "keyword": "die",
    "score": 0.4230488588864879
  },
  {
    "keyword": "another",
    "score": 0.4222204135099066
  },
  {
    "keyword": "chin",
    "score": 0.4184862556356795
  },
  {
    "keyword": "rest",
    "score": 0.41276940409408513
  },
  {
    "keyword": "stuff",
    "score": 0.40364724753465964
  },
  {
    "keyword": "switched",
    "score": 0.40109224346279276
  },
  {
    "keyword": "blah",
    "score": 0.3934005496078344
  },
  {
    "keyword": "kid",
    "score": 0.39125560996806297
  },
  {
    "keyword": "happy",
    "score": 0.3790503226456573
  },
  {
    "keyword": "kidding",
    "score": 0.378907529591328
  },
  {
    "keyword": "found",
    "score": 0.3783346939805246
  },
  {
    "keyword": "calm",
    "score": 0.36644384298765875
  },
  {
    "keyword": "humans",
    "score": 0.36297683532271247
  },
  {
    "keyword": "though",
    "score": 0.356051414468566
  },
  {
    "keyword": "bounty hunter",
    "score": 0.3553192362351807
  },
  {
    "keyword": "messenger",
    "score": 0.35225251111064776
  },
  {
    "keyword": "gun",
    "score": 0.34467500089698855
  },
  {
    "keyword": "lying",
    "score": 0.3429656762597844
  },
  {
    "keyword": "girlfriend",
    "score": 0.3429021967000835
  },
  {
    "keyword": "phone",
    "score": 0.3383987805704179
  },
  {
    "keyword": "form",
    "score": 0.33827316919117045
  },
  {
    "keyword": "happens",
    "score": 0.33738078460313475
  },
  {
    "keyword": "yet",
    "score": 0.33738078460313475
  },
  {
    "keyword": "heard",
    "score": 0.3319041967360853
  },
  {
    "keyword": "watching",
    "score": 0.3319041967360853
  },
  {
    "keyword": "guess",
    "score": 0.3306422151825192
  },
  {
    "keyword": "live",
    "score": 0.32646623048246187
  },
  {
    "keyword": "surely",
    "score": 0.32527022233608693
  },
  {
    "keyword": "demon demon",
    "score": 0.3238660481149555
  },
  {
    "keyword": "pretty",
    "score": 0.3177964301946941
  },
  {
    "keyword": "forget",
    "score": 0.31609835698398797
  },
  {
    "keyword": "missing",
    "score": 0.31609835698398797
  },
  {
    "keyword": "somewhere",
    "score": 0.31609835698398797
  },
  {
    "keyword": "waiting",
    "score": 0.31609835698398797
  },
  {
    "keyword": "ten",
    "score": 0.31411902623586907
  },
  {
    "keyword": "sit",
    "score": 0.312496501022183
  },
  {
    "keyword": "deal",
    "score": 0.3113214069588517
  },
  {
    "keyword": "blind",
    "score": 0.3050788861428174
  },
  {
    "keyword": "three",
    "score": 0.30329621755699054
  },
  {
    "keyword": "wish",
    "score": 0.3011772237142993
  },
  {
    "keyword": "story",
    "score": 0.3008812695931828
  },
  {
    "keyword": "jonathan",
    "score": 0.30038959386224034
  },
  {
    "keyword": "water",
    "score": 0.2975872347893138
  },
  {
    "keyword": "power source",
    "score": 0.29683170094323374
  },
  {
    "keyword": "came",
    "score": 0.296760493300512
  },
  {
    "keyword": "alive",
    "score": 0.29638940773464045
  },
  {
    "keyword": "children",
    "score": 0.29638940773464045
  },
  {
    "keyword": "mind",
    "score": 0.2960942842489862
  },
  {
    "keyword": "weird",
    "score": 0.29300306733217224
  },
  {
    "keyword": "still",
    "score": 0.2914751387832239
  },
  {
    "keyword": "shoot",
    "score": 0.28955345711689556
  },
  {
    "keyword": "saved",
    "score": 0.2881521899032914
  },
  {
    "keyword": "favour",
    "score": 0.28732531763804464
  },
  {
    "keyword": "welcome",
    "score": 0.28707974931507674
  },
  {
    "keyword": "scent",
    "score": 0.28632325684552157
  },
  {
    "keyword": "presents sync",
    "score": 0.2853952548320682
  },
  {
    "keyword": "made",
    "score": 0.2851324723311421
  },
  {
    "keyword": "tomorrow",
    "score": 0.2825538331375367
  },
  {
    "keyword": "pulse",
    "score": 0.2779376493170686
  },
  {
    "keyword": "brilliant",
    "score": 0.2774004937685335
  },
  {
    "keyword": "ears",
    "score": 0.2748234453643639
  },
  {
    "keyword": "child",
    "score": 0.27316521076306427
  },
  {
    "keyword": "balls",
    "score": 0.2726672326523121
  }
]